pybundler/__init__.py
pybundler/get_config.py
pybundler/make_gitignore.py
pybundler/make_init.py
pybundler/make_license.py
pybundler/make_project.py
pybundler/make_readme.py
pybundler/make_setup.py
pybundler/pybundler.py
PyBundleCli-0.0.5.dist-info/LICENSE
PyBundleCli-0.0.5.dist-info/METADATA
PyBundleCli-0.0.5.dist-info/WHEEL
PyBundleCli-0.0.5.dist-info/entry_points.txt
PyBundleCli-0.0.5.dist-info/top_level.txt
PyBundleCli-0.0.5.dist-info/RECORD
