Metadata-Version: 2.1
Name: PyBundleCli
Version: 0.0.5
Summary: bundle python files for command line tools
Home-page: https://github.com/kyohei-horikawa/PyBundleCli
Author: Kyohei Horikawa
Author-email: kyohei3430@gmail.com
License: MIT License        
Platform: UNKNOWN
License-File: LICENSE
Requires-Dist: fire (>=0.4.0)
Requires-Dist: setuptools (>=58.2.0)
